<monitors version="2">
  <configuration>
    <layoutmode>physical</layoutmode>
    <logicalmonitor>
      <x>0</x>
      <y>0</y>
      <scale>1</scale>
      <primary>yes</primary>
      <monitor>
        <monitorspec>
          <connector>DP-3</connector>
          <vendor>GSM</vendor>
          <product>LG ULTRAGEAR</product>
          <serial>311NTWGE5169</serial>
        </monitorspec>
        <mode>
          <width>3440</width>
          <height>1440</height>
          <rate>143.923</rate>
        </mode>
      </monitor>
    </logicalmonitor>
    <logicalmonitor>
      <x>3440</x>
      <y>360</y>
      <scale>1</scale>
      <monitor>
        <monitorspec>
          <connector>DP-2</connector>
          <vendor>VSC</vendor>
          <product>XG2405</product>
          <serial>W9Q210300233</serial>
        </monitorspec>
        <mode>
          <width>1920</width>
          <height>1080</height>
          <rate>144.001</rate>
        </mode>
      </monitor>
    </logicalmonitor>
  </configuration>
</monitors>
